{
    "sampler": "HMC",
    "value": 3,
    "means_array": [
        [
            0.0,
            0.0
        ]
    ],
    "case": "Posterior Samples",
    "dim": 2,
    "samples": [
        [
            -0.8917546522528871,
            -0.46087694724099076
        ],
        [
            5.000931667529828,
            -1.063263042411944
        ],
        [
            -1.6027527487079924,
            -2.091175426000376
        ],
        [
            -0.9383690594212112,
            -2.7823722387624663
        ]
    ]
}