{
    "run_id": 1,
    "case": "multimodal",
    "dim": 2,
    "means_array": [
        [
            0,
            0
        ],
        [
            -5,
            -5
        ],
        [
            40,
            40
        ]
    ],
    "min_mode": [
        -5,
        -5
    ],
    "max_mode": [
        40,
        40
    ],
    "border": [
        11.25,
        11.25
    ],
    "low": [
        -16.25,
        -16.25
    ],
    "high": [
        51.25,
        51.25
    ],
    "samples": [
        {
            "posterior": [
                22.37399010645055,
                40.81826352058109
            ]
        },
        {
            "posterior": [
                -4.930212855603299,
                -10.030168265574329
            ]
        },
        {
            "posterior": [
                -0.42551367653513417,
                3.2211783882507135
            ]
        },
        {
            "posterior": [
                2.8925982869557956,
                1.1340254161786092
            ]
        }
    ]
}