{
    "sampler": "Metro",
    "value": 20,
    "means_array": [
        [
            0.0,
            0.0
        ],
        [
            -19.81387939470339,
            -2.7221651919287297
        ]
    ],
    "case": "Posterior Samples",
    "dim": 2,
    "samples": [
        [
            -0.052154309659196985,
            0.2963977954238688
        ],
        [
            -0.4484369380126676,
            -1.2669569779487277
        ],
        [
            -0.11059247963525631,
            0.9130415485323073
        ],
        [
            0.22169589047181204,
            0.5622493696238392
        ]
    ]
}