{
    "run_id": 1,
    "case": "multimodal",
    "dim": 2,
    "means_array": [
        [
            -5.0,
            0.0
        ],
        [
            5.0,
            0.0
        ]
    ],
    "min_mode": [
        -5.0,
        0.0
    ],
    "max_mode": [
        5.0,
        0.0
    ],
    "border": [
        20.0,
        20.0
    ],
    "low": [
        -30.207399140037136,
        -29.81388547398369
    ],
    "high": [
        29.792600859962864,
        30.18611452601631
    ],
    "samples": [
        {
            "posterior": [
                -5.604126446928536,
                -8.367629384475148
            ]
        }
    ]
}