{
    "sampler": "HMC",
    "value": 0.9,
    "means_array": [
        [
            -1.7435595857211195,
            0.0
        ],
        [
            1.7435595857211195,
            0.0
        ]
    ],
    "case": "Posterior Samples",
    "dim": 2,
    "samples": [
        [
            1.70698961356968,
            -0.1462013160797678
        ],
        [
            1.0692761890945055,
            -0.3726750632496178
        ],
        [
            -3.2585465454214075,
            -1.6808302325817799
        ],
        [
            2.2342793590732963,
            0.08841018701049023
        ]
    ]
}