{
    "run_id": 1,
    "case": "unimodal",
    "dim": 30,
    "low": [
        -90,
        -90,
        -90,
        -90,
        -90,
        -80,
        -80,
        -80,
        -80,
        -80,
        -70,
        -70,
        -70,
        -70,
        -70,
        -60,
        -60,
        -60,
        -60,
        -60,
        -50,
        -50,
        -50,
        -50,
        -50,
        -40,
        -40,
        -40,
        -40,
        -40
    ],
    "high": [
        110,
        110,
        110,
        110,
        110,
        120,
        120,
        120,
        120,
        120,
        130,
        130,
        130,
        130,
        130,
        140,
        140,
        140,
        140,
        140,
        150,
        150,
        150,
        150,
        150,
        160,
        160,
        160,
        160,
        160
    ],
    "means_array": [
        [
            10,
            10,
            10,
            10,
            10,
            20,
            20,
            20,
            20,
            20,
            30,
            30,
            30,
            30,
            30,
            40,
            40,
            40,
            40,
            40,
            50,
            50,
            50,
            50,
            50,
            60,
            60,
            60,
            60,
            60
        ]
    ],
    "samples": [
        {
            "posterior": [
                10.786903682449648,
                39.20428005734675,
                76.71707394755055,
                68.58939722851,
                21.11842151972762,
                -4.154372391683211,
                -59.10588650918431,
                41.47068876714707,
                26.832124193632794,
                -59.184325636654876,
                55.66275401705147,
                17.341495636634534,
                -42.94388392425319,
                119.4775235433911,
                70.78447475250243,
                60.26868832000311,
                123.16499602924995,
                83.92271849860816,
                92.74184238556691,
                1.8367530614322831,
                -12.156111206514986,
                127.78627561521535,
                -26.084436840228562,
                110.72213812486928,
                106.24965229849226,
                133.3479259383515,
                -6.09502160952723,
                0.42246555067781344,
                108.82551530607677,
                157.55763036268013
            ]
        }
    ]
}