{
    "sampler": "HMC",
    "value": 2,
    "means_array": [
        [
            0.0,
            0.0
        ]
    ],
    "case": "Posterior Samples",
    "dim": 2,
    "samples": [
        [
            -0.21287916450272013,
            0.277547158283482
        ],
        [
            -0.18562666801091843,
            -0.23290031378695453
        ],
        [
            -0.012696357697433247,
            -0.34654356936291686
        ],
        [
            0.29295713332689044,
            -0.16201735219169736
        ]
    ]
}