{
    "run_id": 1,
    "case": "unimodal",
    "dim": 5,
    "low": [
        -30.27435004064185,
        -30.088877652903268,
        -30.129666631384374,
        -30.058808681919473,
        -30.01497839053522
    ],
    "high": [
        29.72564995935815,
        29.911122347096732,
        29.870333368615626,
        29.941191318080527,
        29.98502160946478
    ],
    "means_array": [
        [
            0.0,
            0.0,
            0.0,
            0.0,
            0.0
        ]
    ],
    "samples": [
        {
            "posterior": [
                -29.925492890574418,
                16.32704036786262,
                29.133661673640553,
                -15.267984569869908,
                9.643257795760675
            ]
        }
    ]
}