{
    "sampler": "HMC",
    "value": 0.3,
    "means_array": [
        [
            0.0,
            0.0
        ],
        [
            10,
            0
        ]
    ],
    "case": "Warmup Samples",
    "dim": 2,
    "samples": [
        [
            12.627015703305462,
            -1.0964519866292886
        ],
        [
            6.80922995532741,
            -0.7966929131876384
        ],
        [
            20.009546413168927,
            8.061158362416437
        ],
        [
            12.78465838589634,
            4.222494056631454
        ]
    ]
}