{
    "sampler": "Metro",
    "value": 0.9,
    "means_array": [
        [
            0.0,
            0.0
        ]
    ],
    "case": "Posterior Samples",
    "dim": 2,
    "samples": [
        [
            -0.27101854529473624,
            -0.7741595500869753
        ],
        [
            0.9072852383455448,
            0.7119227515203697
        ],
        [
            -1.0014658146298827,
            -1.6786532529240648
        ],
        [
            -0.9853138678642546,
            -0.5830984941861717
        ]
    ]
}