{
    "sampler": "HMC",
    "value": 2,
    "means_array": [
        [
            0.0,
            0.0
        ]
    ],
    "case": "Posterior Samples",
    "dim": 2,
    "samples": [
        [
            0.838318218283729,
            -0.25684317579969684
        ],
        [
            -1.623097456522733,
            0.20050923989825145
        ],
        [
            0.07495269496676522,
            0.09979333560408954
        ],
        [
            -0.04076232703087717,
            2.032994328755858
        ]
    ]
}