{
    "sampler": "Metro",
    "value": 2,
    "means_array": [
        [
            -4.000000002,
            0.0
        ],
        [
            4.000000002,
            0.0
        ]
    ],
    "case": "Warmup Samples",
    "dim": 2,
    "samples": [
        [
            -49.00037404306122,
            -128.9737480711597
        ],
        [
            14.512775036648199,
            9.914418495502654
        ],
        [
            -34.60583779517182,
            115.24544593616534
        ],
        [
            30.95399614727469,
            -39.881462594765054
        ]
    ]
}