{
    "sampler": "DEMetro_Z",
    "value": 6,
    "means_array": [
        [
            -0.936749708899075,
            0.0
        ],
        [
            0.936749708899075,
            0.0
        ]
    ],
    "case": "Posterior Samples",
    "dim": 2,
    "samples": [
        [
            -0.048051957706355876,
            -1.7663901691870776
        ],
        [
            0.47233217489148255,
            1.5128964648466705
        ],
        [
            -0.20228890176702255,
            -0.7862703756061699
        ],
        [
            1.4998510972428971,
            0.497692230608452
        ]
    ]
}