{
    "sampler": "HMC",
    "value": [
        20,
        20
    ],
    "means_array": [
        [
            0,
            0
        ],
        [
            -5,
            -5
        ],
        [
            20,
            20
        ]
    ],
    "case": "Posterior Samples",
    "dim": 2,
    "samples": [
        [
            -4.197461139633672,
            -5.947684900961801
        ],
        [
            19.729017707923308,
            19.35997802353892
        ],
        [
            -0.3479919550876322,
            -0.9432117778024265
        ],
        [
            21.57690749493208,
            20.559365096527284
        ]
    ]
}