{
    "sampler": "Metro",
    "value": 15,
    "means_array": [
        [
            -7.5,
            0.0
        ],
        [
            7.5,
            0.0
        ]
    ],
    "case": "Warmup Samples",
    "dim": 2,
    "samples": [
        [
            -30.453935788577155,
            19.64887911377764
        ],
        [
            -5.158679866429008,
            -17.572446047646668
        ],
        [
            23.39173031812613,
            2.912754508554393
        ],
        [
            5.229295525385716,
            -6.883614205910089
        ]
    ]
}