{
    "sampler": "Metro",
    "value": 6,
    "means_array": [
        [
            -3.0000000015,
            0.0
        ],
        [
            3.0000000015,
            0.0
        ]
    ],
    "case": "Warmup Samples",
    "dim": 2,
    "samples": [
        [
            67.17729675104202,
            -59.10468317882821
        ],
        [
            51.76980840648122,
            81.11263472952781
        ],
        [
            61.76087585142738,
            32.45811337684351
        ],
        [
            41.405648263083535,
            -38.36650121860164
        ]
    ]
}