{
    "sampler": "HMC",
    "value": 5,
    "means_array": [
        [
            -2.5,
            0.0
        ],
        [
            2.5,
            0.0
        ]
    ],
    "case": "Warmup Samples",
    "dim": 2,
    "samples": [
        [
            -7.765096136254566,
            -1.2550268703927536
        ],
        [
            -4.226704506653101,
            -10.206953146558414
        ],
        [
            10.215365775864285,
            12.301207282204349
        ],
        [
            22.81719837129229,
            18.533000202560178
        ]
    ]
}