{
    "sampler": "DEMetro_Z",
    "value": [
        -20,
        0,
        0,
        0,
        0
    ],
    "means_array": [
        [
            -20,
            0,
            0,
            0,
            0
        ],
        [
            -12,
            0,
            0,
            0,
            0
        ],
        [
            -4,
            0,
            0,
            0,
            0
        ],
        [
            4,
            0,
            0,
            0,
            0
        ],
        [
            12,
            0,
            0,
            0,
            0
        ],
        [
            20,
            0,
            0,
            0,
            0
        ]
    ],
    "case": "Warmup Samples",
    "dim": 5,
    "samples": [
        [
            19.6094369438213,
            4.186114983392612,
            -9.342510378768283,
            6.252421404566428,
            -2.4112115072523985
        ],
        [
            -27.275570949786896,
            -5.821987248979104,
            7.814070953647362,
            7.413857387260482,
            -9.840390986359301
        ],
        [
            -26.324725248503764,
            -3.447312720132505,
            5.520730324062017,
            -1.0241085892759185,
            -5.235503425899356
        ],
        [
            15.34725187216178,
            2.4908802091690765,
            -6.483811892694591,
            2.6370147161004716,
            5.317909280767453
        ]
    ]
}