{
    "run_id": 1,
    "case": "multimodal",
    "dim": 2,
    "means_array": [
        [
            0.0,
            0.0
        ],
        [
            4.161913352499667,
            -14.411053994981943
        ]
    ],
    "min_mode": [
        0.0,
        -14.411053994981943
    ],
    "max_mode": [
        4.161913352499667,
        0.0
    ],
    "border": [
        20.0,
        20.156668242943784
    ],
    "low": [
        -27.65558438348481,
        -37.41254865120057
    ],
    "high": [
        32.34441561651519,
        23.057456077630786
    ],
    "samples": [
        {
            "posterior": [
                -9.175960646297987,
                -17.407974052230987
            ]
        },
        {
            "posterior": [
                -4.633061870493808,
                -14.63747245667695
            ]
        },
        {
            "posterior": [
                31.56272117906214,
                -13.8793530125808
            ]
        },
        {
            "posterior": [
                17.735093459745695,
                17.96928354966539
            ]
        }
    ]
}