{
    "sampler": "Metro",
    "value": 0.3,
    "means_array": [
        [
            0.0,
            0.0
        ],
        [
            13,
            0
        ]
    ],
    "case": "Warmup Samples",
    "dim": 2,
    "samples": [
        [
            1.987185822187218,
            2.413329251829338
        ],
        [
            -18.28770728905129,
            3.4078607486114407
        ],
        [
            29.327493356828327,
            -28.97455569621411
        ],
        [
            -20.37486515989186,
            -23.047061851365022
        ]
    ]
}