{
    "run_id": 1,
    "case": "unimodal",
    "dim": 30,
    "low": [
        -100.0,
        -100.0,
        -100.0,
        -100.0,
        -100.0,
        -100.0,
        -100.0,
        -100.0,
        -100.0,
        -100.0,
        -100.0,
        -100.0,
        -100.0,
        -100.0,
        -100.0,
        -100.0,
        -100.0,
        -100.0,
        -100.0,
        -100.0,
        -100.0,
        -100.0,
        -100.0,
        -100.0,
        -100.0,
        -100.0,
        -100.0,
        -100.0,
        -100.0,
        -100.0
    ],
    "high": [
        100.0,
        100.0,
        100.0,
        100.0,
        100.0,
        100.0,
        100.0,
        100.0,
        100.0,
        100.0,
        100.0,
        100.0,
        100.0,
        100.0,
        100.0,
        100.0,
        100.0,
        100.0,
        100.0,
        100.0,
        100.0,
        100.0,
        100.0,
        100.0,
        100.0,
        100.0,
        100.0,
        100.0,
        100.0,
        100.0
    ],
    "means_array": [
        [
            0.0,
            0.0,
            0.0,
            0.0,
            0.0,
            0.0,
            0.0,
            0.0,
            0.0,
            0.0,
            0.0,
            0.0,
            0.0,
            0.0,
            0.0,
            0.0,
            0.0,
            0.0,
            0.0,
            0.0,
            0.0,
            0.0,
            0.0,
            0.0,
            0.0,
            0.0,
            0.0,
            0.0,
            0.0,
            0.0
        ]
    ],
    "samples": [
        {
            "posterior": [
                0.7869036824496476,
                29.20428005734675,
                66.71707394755055,
                58.589397228509995,
                11.118421519727619,
                -24.15437239168321,
                -79.1058865091843,
                21.470688767147067,
                6.832124193632794,
                -79.18432563665488,
                25.66275401705147,
                -12.658504363365466,
                -72.94388392425319,
                89.4775235433911,
                40.78447475250243,
                20.268688320003108,
                83.16499602924995,
                43.92271849860816,
                52.74184238556691,
                -38.16324693856772,
                -62.156111206514986,
                77.78627561521535,
                -76.08443684022856,
                60.722138124869275,
                56.249652298492265,
                73.3479259383515,
                -66.09502160952724,
                -59.57753444932219,
                48.82551530607677,
                97.55763036268013
            ]
        }
    ]
}