{
    "sampler": "HMC",
    "value": 2,
    "means_array": [
        [
            10,
            10
        ]
    ],
    "case": "Posterior Samples",
    "dim": 2,
    "samples": [
        [
            9.297084811230242,
            10.08271819948158
        ],
        [
            9.438885201205377,
            9.744683976978598
        ],
        [
            9.99804932251761,
            10.02787670950376
        ],
        [
            10.903817275230832,
            10.798415736454627
        ]
    ]
}