{
    "sampler": "Metro",
    "value": 2,
    "means_array": [
        [
            0.0,
            0.0
        ],
        [
            10.0,
            0.0
        ]
    ],
    "case": "Warmup Samples",
    "dim": 2,
    "samples": [
        [
            10.861196706125918,
            8.32256205864175
        ],
        [
            -4.0704499396413585,
            -7.527334624856463
        ],
        [
            -6.659770765184429,
            5.273829082716746
        ],
        [
            -6.889900360735598,
            4.258794676491815
        ]
    ]
}