{
    "sampler": "Metro",
    "value": 30,
    "means_array": [
        [
            0,
            0
        ]
    ],
    "case": "Warmup Samples",
    "dim": 2,
    "samples": [
        [
            25.06150070763898,
            -85.47062498626326
        ],
        [
            -18.657212953407836,
            27.085131205524206
        ],
        [
            32.19367113689049,
            17.15478281849784
        ],
        [
            -52.376245277765065,
            -71.08637799408167
        ]
    ]
}