{
    "sampler": "HMC",
    "value": 10,
    "means_array": [
        [
            0.0,
            0.0
        ],
        [
            16,
            0
        ]
    ],
    "case": "Posterior Samples",
    "dim": 2,
    "samples": [
        [
            14.994446670066655,
            -0.26766804281343876
        ],
        [
            -1.2669048469809197,
            2.6697508605547307
        ],
        [
            -0.2736709535560466,
            -0.5940052023458139
        ],
        [
            -1.1772102485063536,
            0.9247297075464925
        ]
    ]
}