{
    "sampler": "Metro",
    "value": 2,
    "means_array": [
        [
            0.0,
            0.0
        ]
    ],
    "case": "Posterior Samples",
    "dim": 2,
    "samples": [
        [
            -1.452108882324206,
            -1.4244416262430244
        ],
        [
            0.1078336531818902,
            0.37674521265412686
        ],
        [
            -0.1967689640288086,
            -1.7104073065207466
        ],
        [
            -1.1133194630621468,
            -0.7598073050848524
        ]
    ]
}